finbro/__init__.py
finbro/client.py
finbro/setup.py
finbro-0.1.0.dist-info/METADATA
finbro-0.1.0.dist-info/WHEEL
finbro-0.1.0.dist-info/top_level.txt
finbro-0.1.0.dist-info/RECORD
